arc_reactor_utility/__init__.py
arc_reactor_utility/folder.py
arc_reactor_utility-1.0.0.dist-info/LICENSE
arc_reactor_utility-1.0.0.dist-info/METADATA
arc_reactor_utility-1.0.0.dist-info/WHEEL
arc_reactor_utility-1.0.0.dist-info/entry_points.txt
arc_reactor_utility-1.0.0.dist-info/top_level.txt
arc_reactor_utility-1.0.0.dist-info/RECORD
