Metadata-Version: 2.1
Name: arc-reactor-utility
Version: 1.0.0
Summary: Utility functions for python
Home-page: https://github.com/Abhishek1009/python-projects/tree/master/arc-reactor-utility
Author: Abhishek Ghosh
Author-email: ghoshabhishek1640@gmail.com
License: UNKNOWN
Platform: UNKNOWN
Classifier: Programming Language :: Python :: 3
Classifier: License :: OSI Approved :: MIT License
Classifier: Operating System :: OS Independent
